VerbalRegex/__init__.py
VerbalRegex-1.0.2.dist-info/METADATA
VerbalRegex-1.0.2.dist-info/WHEEL
VerbalRegex-1.0.2.dist-info/top_level.txt
VerbalRegex-1.0.2.dist-info/RECORD
